torch_ac/__init__.py
torch_ac/format.py
torch_ac/model.py
torch_ac/algos/__init__.py
torch_ac/algos/a2c.py
torch_ac/algos/base.py
torch_ac/algos/ppo.py
torch_ac/utils/__init__.py
torch_ac/utils/dictlist.py
torch_ac/utils/penv.py
torch_ac-1.4.0.dist-info/LICENSE
torch_ac-1.4.0.dist-info/METADATA
torch_ac-1.4.0.dist-info/WHEEL
torch_ac-1.4.0.dist-info/top_level.txt
torch_ac-1.4.0.dist-info/RECORD
