Metadata-Version: 2.1
Name: torch-ac
Version: 1.4.0
Keywords: reinforcement learning,actor-critic,a2c,ppo,multi-processes,gpu
License-File: LICENSE
Requires-Dist: numpy (>=1.13.0)
Requires-Dist: torch (>=1.0.0)
